{"coord":{"lon":21.146,"lat":51.3962},"weather":[{"id":802,"main":"Clouds","description":"scattered clouds","icon":"03d"}],"base":"stations","main":{"temp":284.96,"feels_like":283.45,"temp_min":284.3,"temp_max":285.98,"pressure":1019,"humidity":48,"sea_level":1019,"grnd_level":999},"visibility":10000,"wind":{"speed":1.79,"deg":343,"gust":5.36},"clouds":{"all":40},"dt":1746961680,"sys":{"type":2,"id":19366,"country":"PL","sunrise":1746931809,"sunset":1746987211},"timezone":7200,"id":760778,"name":"Radom","cod":200}